server.py
lyzr_single_tool-0.1.3.dist-info/METADATA
lyzr_single_tool-0.1.3.dist-info/WHEEL
lyzr_single_tool-0.1.3.dist-info/entry_points.txt
lyzr_single_tool-0.1.3.dist-info/top_level.txt
lyzr_single_tool-0.1.3.dist-info/RECORD
